benchmarks
deepharvest
examples
tests
venv
