Metadata-Version: 2.4
Name: deepharvest
Version: 1.0.4
Summary: The world's most complete, resilient, multilingual web crawler
Home-page: https://github.com/Anajrajeev/DeepHarvest
Author: DeepHarvest Contributors
License-Expression: Apache-2.0
Project-URL: Homepage, https://github.com/Anajrajeev/DeepHarvest
Project-URL: Documentation, https://github.com/Anajrajeev/DeepHarvest
Project-URL: Repository, https://github.com/Anajrajeev/DeepHarvest
Project-URL: Bug Tracker, https://github.com/Anajrajeev/DeepHarvest/issues
Classifier: Development Status :: 4 - Beta
Classifier: Intended Audience :: Developers
Classifier: Topic :: Internet :: WWW/HTTP :: Indexing/Search
Classifier: Topic :: Software Development :: Libraries :: Python Modules
Classifier: Programming Language :: Python :: 3
Classifier: Programming Language :: Python :: 3.9
Classifier: Programming Language :: Python :: 3.10
Classifier: Programming Language :: Python :: 3.11
Classifier: Programming Language :: Python :: 3.12
Requires-Python: >=3.9
License-File: LICENSE
Requires-Dist: aiohttp>=3.9.0
Requires-Dist: lxml>=4.9.0
Requires-Dist: beautifulsoup4>=4.12.0
Requires-Dist: html5lib>=1.1
Requires-Dist: playwright>=1.40.0
Requires-Dist: PyMuPDF>=1.23.0
Requires-Dist: python-docx>=1.1.0
Requires-Dist: python-pptx>=0.6.21
Requires-Dist: openpyxl>=3.1.0
Requires-Dist: Pillow>=10.1.0
Requires-Dist: pytesseract>=0.3.10
Requires-Dist: extruct>=0.15.0
Requires-Dist: chardet>=5.2.0
Requires-Dist: charset-normalizer>=3.3.0
Requires-Dist: langdetect>=1.0.9
Requires-Dist: scikit-learn>=1.3.0
Requires-Dist: numpy>=1.24.0
Requires-Dist: simhash>=2.1.0
Requires-Dist: datasketch>=1.6.0
Requires-Dist: mmh3>=4.0.0
Requires-Dist: redis[hiredis]>=5.0.0
Requires-Dist: boto3>=1.28.0
Requires-Dist: psycopg2-binary>=2.9.0
Requires-Dist: click>=8.1.0
Requires-Dist: pyyaml>=6.0
Requires-Dist: prometheus-client>=0.19.0
Requires-Dist: tqdm>=4.66.0
Requires-Dist: python-dateutil>=2.8.0
Requires-Dist: networkx>=3.0
Requires-Dist: pandas>=2.0.0
Requires-Dist: setuptools>=61.0
Provides-Extra: dev
Requires-Dist: pytest>=7.4.0; extra == "dev"
Requires-Dist: pytest-asyncio>=0.21.0; extra == "dev"
Requires-Dist: pytest-cov>=4.1.0; extra == "dev"
Requires-Dist: black>=23.11.0; extra == "dev"
Requires-Dist: flake8>=6.1.0; extra == "dev"
Requires-Dist: mypy>=1.7.0; extra == "dev"
Requires-Dist: sphinx>=7.2.0; extra == "dev"
Requires-Dist: sphinx-rtd-theme>=2.0.0; extra == "dev"
Requires-Dist: psutil>=5.9.0; extra == "dev"
Provides-Extra: full
Requires-Dist: torch>=2.1.0; extra == "full"
Requires-Dist: transformers>=4.35.0; extra == "full"
Requires-Dist: faiss-cpu>=1.7.4; extra == "full"
Requires-Dist: chromadb>=0.4.0; extra == "full"
Requires-Dist: pyarrow>=14.0.0; extra == "full"
Dynamic: home-page
Dynamic: license-file
Dynamic: requires-python
